{
  "produtos": [
    {
      "codigo": "CLT00001M",
      "tipo": "CJT Leg + Top",
      "produto": "CJT Leg + Top Rosa Cand M",
      "cor": "Rosa Cand",
      "tamanho": "M",
      "precoVenda": 189.9,
      "precoVenda3x": 203.7,
      "estoque": 1,
      "condicional": 0,
      "id": "1764701907234_prod_xeud028mj",
      "dataCadastro": "2025-12-02T18:58:27.234Z",
      "ultimaAtualizacao": "2025-12-02T18:58:27.234Z"
    },
    {
      "codigo": "CLT00001G",
      "tipo": "CJT Leg + Top",
      "produto": "CJT Leg + Top Terracota G",
      "cor": "Terracota",
      "tamanho": "G",
      "precoVenda": 189.9,
      "precoVenda3x": 203.7,
      "estoque": 1,
      "condicional": 0,
      "id": "1764701907234_prod_ltnpxhv1e",
      "dataCadastro": "2025-12-02T18:58:27.234Z",
      "ultimaAtualizacao": "2025-12-02T18:58:27.234Z"
    },
    {
      "codigo": "CST00001G",
      "tipo": "CJT Sht + Top",
      "produto": "CJT Sht + Top Branco G",
      "cor": "Branco",
      "tamanho": "G",
      "precoVenda": 154.9,
      "precoVenda3x": 167.7,
      "estoque": 1,
      "condicional": 0,
      "id": "1764701907234_prod_kzs5q5bov",
      "dataCadastro": "2025-12-02T18:58:27.234Z",
      "ultimaAtualizacao": "2025-12-02T18:58:27.235Z"
    },
    {
      "codigo": "CST00001M",
      "tipo": "CJT Sht + Top",
      "produto": "CJT Sht + Top Branco M",
      "cor": "Branco",
      "tamanho": "M",
      "precoVenda": 154.9,
      "precoVenda3x": 167.7,
      "estoque": 1,
      "condicional": 0,
      "id": "1764701907235_prod_ajh1xvmmn",
      "dataCadastro": "2025-12-02T18:58:27.235Z",
      "ultimaAtualizacao": "2025-12-02T18:58:27.235Z"
    },
    {
      "codigo": "MCQ00001G",
      "tipo": "Macaquinho",
      "produto": "Macaquinho Azul Cand G",
      "cor": "Azul Cand",
      "tamanho": "G",
      "precoVenda": 139.9,
      "precoVenda3x": 149.7,
      "estoque": 1,
      "condicional": 0,
      "id": "1764701907235_prod_924jtzph2",
      "dataCadastro": "2025-12-02T18:58:27.235Z",
      "ultimaAtualizacao": "2025-12-02T18:58:27.235Z"
    },
    {
      "codigo": "MCQ00001M",
      "tipo": "Macaquinho",
      "produto": "Macaquinho Militar M",
      "cor": "Militar",
      "tamanho": "M",
      "precoVenda": 139.9,
      "precoVenda3x": 149.7,
      "estoque": 1,
      "condicional": 0,
      "id": "1764701907235_prod_ak6xe0hir",
      "dataCadastro": "2025-12-02T18:58:27.235Z",
      "ultimaAtualizacao": "2025-12-02T18:58:27.235Z"
    },
    {
      "codigo": "MCQ00001P",
      "tipo": "Macaquinho",
      "produto": "Macaquinho Rosa Cand P",
      "cor": "Rosa Cand",
      "tamanho": "P",
      "precoVenda": 139.9,
      "precoVenda3x": 149.7,
      "estoque": 1,
      "condicional": 0,
      "id": "1764701907235_prod_k4qsokwvl",
      "dataCadastro": "2025-12-02T18:58:27.235Z",
      "ultimaAtualizacao": "2025-12-02T18:58:27.235Z"
    },
    {
      "codigo": "CMT00001M",
      "tipo": "Camiseta",
      "produto": "Camiseta Militar M",
      "cor": "Militar",
      "tamanho": "M",
      "precoVenda": 79.9,
      "precoVenda3x": 86.7,
      "estoque": 1,
      "condicional": 0,
      "id": "1764701907235_prod_ex7msl84b",
      "dataCadastro": "2025-12-02T18:58:27.235Z",
      "ultimaAtualizacao": "2025-12-02T18:58:27.235Z"
    },
    {
      "codigo": "CMT00001GG",
      "tipo": "Camiseta",
      "produto": "Camiseta Militar GG",
      "cor": "Militar",
      "tamanho": "GG",
      "precoVenda": 79.9,
      "precoVenda3x": 86.7,
      "estoque": 1,
      "condicional": 0,
      "id": "1764701907235_prod_4ecx2mzmx",
      "dataCadastro": "2025-12-02T18:58:27.235Z",
      "ultimaAtualizacao": "2025-12-02T18:58:27.235Z"
    },
    {
      "codigo": "RGT00001M",
      "tipo": "Regata",
      "produto": "Regata Preto M",
      "cor": "Preto",
      "tamanho": "M",
      "precoVenda": 69.9,
      "precoVenda3x": 74.7,
      "estoque": 1,
      "condicional": 0,
      "id": "1764701907235_prod_546kad8l9",
      "dataCadastro": "2025-12-02T18:58:27.235Z",
      "ultimaAtualizacao": "2025-12-02T18:58:27.235Z"
    },
    {
      "codigo": "RGT00001GG",
      "tipo": "Regata",
      "produto": "Regata Marinho GG",
      "cor": "Marinho",
      "tamanho": "GG",
      "precoVenda": 69.9,
      "precoVenda3x": 74.7,
      "estoque": 1,
      "condicional": 0,
      "id": "1764701907235_prod_dohoyjf7o",
      "dataCadastro": "2025-12-02T18:58:27.235Z",
      "ultimaAtualizacao": "2025-12-02T18:58:27.235Z"
    },
    {
      "codigo": "CLT00001GG",
      "tipo": "CJT Leg + Top",
      "produto": "CJT Leg + Top Militar GG",
      "cor": "Militar",
      "tamanho": "GG",
      "precoVenda": 189.9,
      "precoVenda3x": 203.7,
      "estoque": 1,
      "condicional": 0,
      "id": "1764701907235_prod_1uee44um4",
      "dataCadastro": "2025-12-02T18:58:27.235Z",
      "ultimaAtualizacao": "2025-12-02T18:58:27.235Z"
    },
    {
      "codigo": "CST00001GG",
      "tipo": "CJT Sht + Top",
      "produto": "CJT Sht + Top Azul Cand GG",
      "cor": "Azul Cand",
      "tamanho": "GG",
      "precoVenda": 154.9,
      "precoVenda3x": 167.7,
      "estoque": 1,
      "condicional": 0,
      "id": "1764701907235_prod_uhhpz5tdw",
      "dataCadastro": "2025-12-02T18:58:27.235Z",
      "ultimaAtualizacao": "2025-12-02T18:58:27.235Z"
    }
  ],
  "movimentacoes": [],
  "compras": [
    {
      "dataCompra": "2025-11-20T03:00:00.000Z",
      "fornecedor": "Three Corpus",
      "codigoFornecedor": "1",
      "formaPagamentoCompra": "Cartão Crédito",
      "parcelas": 3,
      "itens": [
        {
          "tipo": "CJT Leg + Top",
          "cor": "Lilás",
          "tamanho": "M",
          "codigoInterno": "CLT00001M",
          "produto": "CJT Leg + Top Lilás M",
          "custoUnitario": 99.9,
          "precoSugerido": 199.8,
          "precoVendaVista": 189.9,
          "precoVenda3x": 203.7,
          "lucroVista": 90.09009009009009,
          "lucro3x": 79.74058060531189,
          "custo3x": 13.43,
          "devolvido": false
        },
        {
          "tipo": "CJT Leg + Top",
          "cor": "Esmeralda",
          "tamanho": "G",
          "codigoInterno": "CLT00001G",
          "produto": "CJT Leg + Top Esmeralda G",
          "custoUnitario": 99.9,
          "precoSugerido": 199.8,
          "precoVendaVista": 189.9,
          "precoVenda3x": 203.7,
          "lucroVista": 90.09009009009009,
          "lucro3x": 79.74058060531189,
          "custo3x": 13.43,
          "devolvido": false
        },
        {
          "tipo": "CJT Leg + Top",
          "cor": "Marinho",
          "tamanho": "M",
          "codigoInterno": "CLT00001M",
          "produto": "CJT Leg + Top Marinho M",
          "custoUnitario": 99.9,
          "precoSugerido": 199.8,
          "precoVendaVista": 189.9,
          "precoVenda3x": 203.7,
          "lucroVista": 90.09009009009009,
          "lucro3x": 79.74058060531189,
          "custo3x": 13.43,
          "devolvido": false
        },
        {
          "tipo": "CJT Leg + Top",
          "cor": "Cinza",
          "tamanho": "M",
          "codigoInterno": "CLT00001M",
          "produto": "CJT Leg + Top Cinza M",
          "custoUnitario": 99.9,
          "precoSugerido": 199.8,
          "precoVendaVista": 189.9,
          "precoVenda3x": 203.7,
          "lucroVista": 90.09009009009009,
          "lucro3x": 79.74058060531189,
          "custo3x": 13.43,
          "devolvido": false
        },
        {
          "tipo": "CJT Leg + Top",
          "cor": "Preto",
          "tamanho": "G",
          "codigoInterno": "CLT00001G",
          "produto": "CJT Leg + Top Preto G",
          "custoUnitario": 99.9,
          "precoSugerido": 199.8,
          "precoVendaVista": 189.9,
          "precoVenda3x": 203.7,
          "lucroVista": 90.09009009009009,
          "lucro3x": 79.74058060531189,
          "custo3x": 13.43,
          "devolvido": false
        },
        {
          "tipo": "CJT Leg + Top",
          "cor": "Militar",
          "tamanho": "M",
          "codigoInterno": "CLT00001M",
          "produto": "CJT Leg + Top Militar M",
          "custoUnitario": 99.9,
          "precoSugerido": 199.8,
          "precoVendaVista": 189.9,
          "precoVenda3x": 203.7,
          "lucroVista": 90.09009009009009,
          "lucro3x": 79.74058060531189,
          "custo3x": 13.43,
          "devolvido": false
        },
        {
          "tipo": "CJT Leg + Top",
          "cor": "Terracota",
          "tamanho": "G",
          "codigoInterno": "CLT00001G",
          "produto": "CJT Leg + Top Terracota G",
          "custoUnitario": 99.9,
          "precoSugerido": 199.8,
          "precoVendaVista": 189.9,
          "precoVenda3x": 203.7,
          "lucroVista": 90.09009009009009,
          "lucro3x": 79.74058060531189,
          "custo3x": 13.43,
          "devolvido": false
        },
        {
          "tipo": "CJT Leg + Top",
          "cor": "Rosa Cand",
          "tamanho": "M",
          "codigoInterno": "CLT00001M",
          "produto": "CJT Leg + Top Rosa Cand M",
          "custoUnitario": 99.9,
          "precoSugerido": 199.8,
          "precoVendaVista": 189.9,
          "precoVenda3x": 203.7,
          "lucroVista": 90.09009009009009,
          "lucro3x": 79.74058060531189,
          "custo3x": 13.43,
          "devolvido": false
        },
        {
          "tipo": "CJT Sht + Top",
          "cor": "Militar",
          "tamanho": "G",
          "codigoInterno": "CST00001G",
          "produto": "CJT Sht + Top Militar G",
          "custoUnitario": 80,
          "precoSugerido": 160,
          "precoVendaVista": 154.9,
          "precoVenda3x": 167.7,
          "lucroVista": 93.625,
          "lucro3x": 84.36675461741422,
          "custo3x": 10.96,
          "devolvido": false
        },
        {
          "tipo": "CJT Sht + Top",
          "cor": "Petroleo",
          "tamanho": "G",
          "codigoInterno": "CST00001G",
          "produto": "CJT Sht + Top Petroleo G",
          "custoUnitario": 80,
          "precoSugerido": 160,
          "precoVendaVista": 154.9,
          "precoVenda3x": 167.7,
          "lucroVista": 93.625,
          "lucro3x": 84.36675461741422,
          "custo3x": 10.96,
          "devolvido": false
        },
        {
          "tipo": "CJT Sht + Top",
          "cor": "Branco",
          "tamanho": "M",
          "codigoInterno": "CST00001M",
          "produto": "CJT Sht + Top Branco M",
          "custoUnitario": 80,
          "precoSugerido": 160,
          "precoVendaVista": 154.9,
          "precoVenda3x": 167.7,
          "lucroVista": 93.625,
          "lucro3x": 84.36675461741422,
          "custo3x": 10.96,
          "devolvido": false
        },
        {
          "tipo": "CJT Sht + Top",
          "cor": "Branco",
          "tamanho": "G",
          "codigoInterno": "CST00001G",
          "produto": "CJT Sht + Top Branco G",
          "custoUnitario": 80,
          "precoSugerido": 160,
          "precoVendaVista": 154.9,
          "precoVenda3x": 167.7,
          "lucroVista": 93.625,
          "lucro3x": 84.36675461741422,
          "custo3x": 10.96,
          "devolvido": false
        },
        {
          "tipo": "Macaquinho",
          "cor": "Lilás",
          "tamanho": "G",
          "codigoInterno": "MCQ00001G",
          "produto": "Macaquinho Lilás G",
          "custoUnitario": 69.9,
          "precoSugerido": 139.8,
          "precoVendaVista": 139.9,
          "precoVenda3x": 149.7,
          "lucroVista": 100.14306151645206,
          "lucro3x": 87.57047988973811,
          "custo3x": 9.91,
          "devolvido": false
        },
        {
          "tipo": "Macaquinho",
          "cor": "Azul Cand",
          "tamanho": "M",
          "codigoInterno": "MCQ00001M",
          "produto": "Macaquinho Azul Cand M",
          "custoUnitario": 69.9,
          "precoSugerido": 139.8,
          "precoVendaVista": 139.9,
          "precoVenda3x": 149.7,
          "lucroVista": 100.14306151645206,
          "lucro3x": 87.57047988973811,
          "custo3x": 9.91,
          "devolvido": false
        },
        {
          "tipo": "Macaquinho",
          "cor": "Azul Cand",
          "tamanho": "G",
          "codigoInterno": "MCQ00001G",
          "produto": "Macaquinho Azul Cand G",
          "custoUnitario": 69.9,
          "precoSugerido": 139.8,
          "precoVendaVista": 139.9,
          "precoVenda3x": 149.7,
          "lucroVista": 100.14306151645206,
          "lucro3x": 87.57047988973811,
          "custo3x": 9.91,
          "devolvido": false
        },
        {
          "tipo": "Macaquinho",
          "cor": "Menta",
          "tamanho": "M",
          "codigoInterno": "MCQ00001M",
          "produto": "Macaquinho Menta M",
          "custoUnitario": 69.9,
          "precoSugerido": 139.8,
          "precoVendaVista": 139.9,
          "precoVenda3x": 149.7,
          "lucroVista": 100.14306151645206,
          "lucro3x": 87.57047988973811,
          "custo3x": 9.91,
          "devolvido": false
        },
        {
          "tipo": "Macaquinho",
          "cor": "Rosa Cand",
          "tamanho": "P",
          "codigoInterno": "MCQ00001P",
          "produto": "Macaquinho Rosa Cand P",
          "custoUnitario": 69.9,
          "precoSugerido": 139.8,
          "precoVendaVista": 139.9,
          "precoVenda3x": 149.7,
          "lucroVista": 100.14306151645206,
          "lucro3x": 87.57047988973811,
          "custo3x": 9.91,
          "devolvido": false
        },
        {
          "tipo": "Macaquinho",
          "cor": "Militar",
          "tamanho": "M",
          "codigoInterno": "MCQ00001M",
          "produto": "Macaquinho Militar M",
          "custoUnitario": 69.9,
          "precoSugerido": 139.8,
          "precoVendaVista": 139.9,
          "precoVenda3x": 149.7,
          "lucroVista": 100.14306151645206,
          "lucro3x": 87.57047988973811,
          "custo3x": 9.91,
          "devolvido": false
        },
        {
          "tipo": "Camiseta",
          "cor": "Militar",
          "tamanho": "M",
          "codigoInterno": "CMT00001M",
          "produto": "Camiseta Militar M",
          "custoUnitario": 49.9,
          "precoSugerido": 99.8,
          "precoVendaVista": 79.9,
          "precoVenda3x": 86.7,
          "lucroVista": 60.12024048096194,
          "lucro3x": 56.07560756075609,
          "custo3x": 5.65,
          "devolvido": false
        },
        {
          "tipo": "Camiseta",
          "cor": "Militar",
          "tamanho": "GG",
          "codigoInterno": "CMT00001GG",
          "produto": "Camiseta Militar GG",
          "custoUnitario": 49.9,
          "precoSugerido": 99.8,
          "precoVendaVista": 79.9,
          "precoVenda3x": 86.7,
          "lucroVista": 60.12024048096194,
          "lucro3x": 56.07560756075609,
          "custo3x": 5.65,
          "devolvido": false
        },
        {
          "tipo": "Regata",
          "cor": "Branco",
          "tamanho": "M",
          "codigoInterno": "RGT00001M",
          "produto": "Regata Branco M",
          "custoUnitario": 39.9,
          "precoSugerido": 79.8,
          "precoVendaVista": 69.9,
          "precoVenda3x": 74.7,
          "lucroVista": 75.18796992481205,
          "lucro3x": 66.4809449520838,
          "custo3x": 4.97,
          "devolvido": false
        },
        {
          "tipo": "Regata",
          "cor": "Marinho",
          "tamanho": "GG",
          "codigoInterno": "RGT00001GG",
          "produto": "Regata Marinho GG",
          "custoUnitario": 39.9,
          "precoSugerido": 79.8,
          "precoVendaVista": 69.9,
          "precoVenda3x": 74.7,
          "lucroVista": 75.18796992481205,
          "lucro3x": 66.4809449520838,
          "custo3x": 4.97,
          "devolvido": false
        },
        {
          "tipo": "Regata",
          "cor": "Preto",
          "tamanho": "M",
          "codigoInterno": "RGT00001M",
          "produto": "Regata Preto M",
          "custoUnitario": 39.9,
          "precoSugerido": 79.8,
          "precoVendaVista": 69.9,
          "precoVenda3x": 74.7,
          "lucroVista": 75.18796992481205,
          "lucro3x": 66.4809449520838,
          "custo3x": 4.97,
          "devolvido": false
        },
        {
          "tipo": "CJT Leg + Top",
          "cor": "Marinho",
          "tamanho": "GG",
          "codigoInterno": "CLT00001GG",
          "produto": "CJT Leg + Top Marinho GG",
          "custoUnitario": 99.9,
          "precoSugerido": 199.8,
          "precoVendaVista": 189.9,
          "precoVenda3x": 203.7,
          "lucroVista": 90.09009009009009,
          "lucro3x": 79.74058060531189,
          "custo3x": 13.43,
          "devolvido": false
        },
        {
          "tipo": "CJT Leg + Top",
          "cor": "Militar",
          "tamanho": "GG",
          "codigoInterno": "CLT00001GG",
          "produto": "CJT Leg + Top Militar GG",
          "custoUnitario": 99.9,
          "precoSugerido": 199.8,
          "precoVendaVista": 189.9,
          "precoVenda3x": 203.7,
          "lucroVista": 90.09009009009009,
          "lucro3x": 79.74058060531189,
          "custo3x": 13.43,
          "devolvido": false
        },
        {
          "tipo": "CJT Sht + Top",
          "cor": "Azul Cand",
          "tamanho": "GG",
          "codigoInterno": "CST00001GG",
          "produto": "CJT Sht + Top Azul Cand GG",
          "custoUnitario": 80,
          "precoSugerido": 160,
          "precoVendaVista": 154.9,
          "precoVenda3x": 167.7,
          "lucroVista": 93.625,
          "lucro3x": 84.36675461741422,
          "custo3x": 10.96,
          "devolvido": false
        }
      ],
      "id": "1764701907234",
      "dataCadastro": "2025-12-02T18:58:27.234Z",
      "ultimaAtualizacao": "2025-12-02T18:58:27.234Z"
    }
  ],
  "fornecedores": [
    {
      "nomeFantasia": "Three Corpus",
      "razaoSocial": "Three Corpus",
      "cnpj": "11.111.111/1111-11",
      "rua": "Afonso Pensa",
      "numero": "3628",
      "complemento": "",
      "cep": "33333-333",
      "bairro": "Centro",
      "cidade": "Governador Valadares",
      "estado": "MG",
      "telefone": "(33) 99133-5972",
      "nomeContato": "Soraia",
      "codigo": "1",
      "id": "1764700075925",
      "dataCadastro": "2025-12-02T18:27:55.925Z",
      "ultimaAtualizacao": "2025-12-02T18:27:55.925Z"
    }
  ],
  "condicionais": [],
  "vendas": [],
  "investimentos": [],
  "caixa": [],
  "contasAReceber": [],
  "contasAPagar": [
    {
      "id": "1764701907235_1_i89kgldm1",
      "dataCompra": "2025-11-20T03:00:00.000Z",
      "dataVencimento": "2025-12-10T03:00:00.000Z",
      "fornecedor": "Three Corpus",
      "codigoCompra": "1764701907234",
      "descricao": "Compra Three Corpus - Parcela 1/3",
      "valor": 679.3000000000003,
      "formaPagamento": "Cartão Crédito",
      "parcela": 1,
      "totalParcelas": 3,
      "pago": false,
      "valorPago": 0,
      "dataCadastro": "2025-12-02T18:58:27.235Z",
      "ultimaAtualizacao": "2025-12-02T22:30:50.179Z",
      "dataPagamento": null
    },
    {
      "id": "1764701907235_2_o7cekyg58",
      "dataCompra": "2025-11-20T03:00:00.000Z",
      "dataVencimento": "2026-01-10T03:00:00.000Z",
      "fornecedor": "Three Corpus",
      "codigoCompra": "1764701907234",
      "descricao": "Compra Three Corpus - Parcela 2/3",
      "valor": 679.3000000000003,
      "formaPagamento": "Cartão Crédito",
      "parcela": 2,
      "totalParcelas": 3,
      "pago": false,
      "valorPago": 0,
      "dataCadastro": "2025-12-02T18:58:27.235Z",
      "ultimaAtualizacao": "2025-12-02T22:30:59.474Z",
      "dataPagamento": null
    },
    {
      "id": "1764701907235_3_g4fnb8hsh",
      "dataCompra": "2025-11-20T03:00:00.000Z",
      "dataVencimento": "2026-02-10T03:00:00.000Z",
      "fornecedor": "Three Corpus",
      "codigoCompra": "1764701907234",
      "descricao": "Compra Three Corpus - Parcela 3/3",
      "valor": 679.3000000000003,
      "formaPagamento": "Cartão Crédito",
      "parcela": 3,
      "totalParcelas": 3,
      "pago": false,
      "valorPago": 0,
      "dataCadastro": "2025-12-02T18:58:27.235Z",
      "ultimaAtualizacao": "2025-12-02T22:31:09.267Z",
      "dataPagamento": null
    },
    {
      "fornecedor": "Shopee",
      "descricao": "1000 Etiquetas",
      "valor": 95.03,
      "dataVencimento": "2025-12-10T03:00:00.000Z",
      "formaPagamento": "Cartão Crédito",
      "dataPagamento": null,
      "valorPago": 0,
      "pago": false,
      "id": "1764715037565_14vkunayu",
      "dataCadastro": "2025-12-02T22:37:17.565Z",
      "ultimaAtualizacao": "2025-12-02T22:37:17.565Z"
    },
    {
      "fornecedor": "Shopee",
      "descricao": "1000 Lacres para etiquetas",
      "valor": 23.9,
      "dataVencimento": "2025-12-10T03:00:00.000Z",
      "formaPagamento": "Cartão Crédito",
      "dataPagamento": null,
      "valorPago": 0,
      "pago": false,
      "id": "1764715069675_o26nszab3",
      "dataCadastro": "2025-12-02T22:37:49.675Z",
      "ultimaAtualizacao": "2025-12-02T22:37:49.675Z"
    },
    {
      "fornecedor": "Shopee",
      "descricao": "300 Adesivos",
      "valor": 22.99,
      "dataVencimento": "2025-12-10T03:00:00.000Z",
      "formaPagamento": "Cartão Crédito",
      "dataPagamento": null,
      "valorPago": 0,
      "pago": false,
      "id": "1764715102247_f2zyo8uha",
      "dataCadastro": "2025-12-02T22:38:22.247Z",
      "ultimaAtualizacao": "2025-12-02T22:38:22.247Z"
    },
    {
      "fornecedor": "JP Embalagens",
      "descricao": "Sacolas",
      "valor": 66.6,
      "dataVencimento": "2025-12-10T03:00:00.000Z",
      "formaPagamento": "Cartão Crédito",
      "dataPagamento": null,
      "valorPago": 0,
      "pago": false,
      "id": "1764715133623_8vgtz2m8f",
      "dataCadastro": "2025-12-02T22:38:53.624Z",
      "ultimaAtualizacao": "2025-12-02T22:38:53.624Z"
    }
  ],
  "cores": [
    "Azul Cand",
    "Branco",
    "Cinza",
    "Esmeralda",
    "Lilás",
    "Marinho",
    "Menta",
    "Militar",
    "Petroleo",
    "Preto",
    "Pink",
    "Rosa Cand",
    "Terracota"
  ]
}